havaiana
