Metadata-Version: 1.0
Name: Havaiana
Version: 2.4.1
Summary: A GUI for Ojota - Alows to edit, create and remove elements
Home-page: http://pypi.python.org/pypi/Havaiana/
Author: Felipe Lerena
Author-email: felipelerena@gmail.com
License: LICENSE.txt
Platform: UNKNOWN
